tsellm/__init__.py
tsellm/__main__.py
tsellm/__version__.py
tsellm/cli.py
tsellm/core.py
tsellm-0.1.0.dist-info/licenses/LICENSE
tsellm-0.1.0.dist-info/METADATA
tsellm-0.1.0.dist-info/WHEEL
tsellm-0.1.0.dist-info/entry_points.txt
tsellm-0.1.0.dist-info/top_level.txt
tsellm-0.1.0.dist-info/RECORD
