Metadata-Version: 2.4
Name: tsellm
Version: 0.1.0
Summary: Use LLMs in SQLite and DuckDB
Home-page: https://github.com/Florents-Tselai/tsellm
Author: Florents Tselai
License: BSD License
Project-URL: Issues, https://github.com/Florents-Tselai/tsellm/issues
Project-URL: CI, https://github.com/Florents-Tselai/tsellm/actions
Project-URL: Changelog, https://github.com/Florents-Tselai/tsellm/releases
Requires-Python: >=3.11
License-File: LICENSE
Requires-Dist: llm
Requires-Dist: setuptools
Requires-Dist: pip
Requires-Dist: duckdb
Provides-Extra: test
Requires-Dist: pytest; extra == "test"
Requires-Dist: pytest-cov; extra == "test"
Requires-Dist: black; extra == "test"
Requires-Dist: ruff; extra == "test"
Requires-Dist: sqlite_utils; extra == "test"
Requires-Dist: llm-markov; extra == "test"
Requires-Dist: llm-embed-hazo==0.2.1; extra == "test"
Dynamic: author
Dynamic: description
Dynamic: description-content-type
Dynamic: home-page
Dynamic: license
Dynamic: license-file
Dynamic: project-url
Dynamic: provides-extra
Dynamic: requires-dist
Dynamic: requires-python
Dynamic: summary
